[{"comp_id":"1399","season":"2016/2017","round":"20","stage_id":"13991081","comp_group":null,"country":"Spain","team_id":"16110","team_name":"Real Madrid","status":"same","recent_form":"WWLWW","position":"1","overall_gp":"19","overall_w":"14","overall_d":"4","overall_l":"1","overall_gs":"51","overall_ga":"17","home_gp":"11","home_w":"9","home_d":"2","home_l":"0","home_gs":"29","home_ga":"10","away_gp":"8","away_w":"5","away_d":"2","away_l":"1","away_gs":"22","away_ga":"7","gd":"34","points":"46","description":"Promotion - Champions League (Group Stage)"},{"comp_id":"1399","season":"2016/2017","round":"20","stage_id":"13991081","comp_group":null,"country":"Spain","team_id":"15702","team_name":"Barcelona","status":"same","recent_form":"DWWDW","position":"2","overall_gp":"20","overall_w":"12","overall_d":"6","overall_l":"2","overall_gs":"52","overall_ga":"18","home_gp":"9","home_w":"5","home_d":"3","home_l":"1","home_gs":"23","home_ga":"7","away_gp":"11","away_w":"7","away_d":"3","away_l":"1","away_gs":"29","away_ga":"11","gd":"34","points":"42","description":"Promotion - Champions League (Group Stage)"},{"comp_id":"1399","season":"2016/2017","round":"20","stage_id":"13991081","comp_group":null,"country":"Spain","team_id":"16175","team_name":"Sevilla","status":"same","recent_form":"LWWWW","position":"3","overall_gp":"20","overall_w":"13","overall_d":"3","overall_l":"4","overall_gs":"43","overall_ga":"28","home_gp":"9","home_w":"8","home_d":"0","home_l":"1","home_gs":"21","home_ga":"11","away_gp":"11","away_w":"5","away_d":"3","away_l":"3","away_gs":"22","away_ga":"17","gd":"15","points":"42","description":"Promotion - Champions League (Group Stage)"},{"comp_id":"1399","season":"2016/2017","round":"20","stage_id":"13991081","comp_group":null,"country":"Spain","team_id":"15692","team_name":"Atl. Madrid","status":"same","recent_form":"DDWWW","position":"4","overall_gp":"20","overall_w":"10","overall_d":"6","overall_l":"4","overall_gs":"34","overall_ga":"16","home_gp":"9","home_w":"6","home_d":"2","home_l":"1","home_gs":"20","home_ga":"7","away_gp":"11","away_w":"4","away_d":"4","away_l":"3","away_gs":"14","away_ga":"9","gd":"18","points":"36","description":"Promotion - Champions League (Qualification)"},{"comp_id":"1399","season":"2016/2017","round":"20","stage_id":"13991081","comp_group":null,"country":"Spain","team_id":"16117","team_name":"Real Sociedad","status":"same","recent_form":"LWWLW","position":"5","overall_gp":"20","overall_w":"11","overall_d":"2","overall_l":"7","overall_gs":"31","overall_ga":"28","home_gp":"10","home_w":"6","home_d":"2","home_l":"2","home_gs":"16","home_ga":"12","away_gp":"10","away_w":"5","away_d":"0","away_l":"5","away_gs":"15","away_ga":"16","gd":"3","points":"35","description":"Promotion - Europa League (Group Stage)"},{"comp_id":"1399","season":"2016/2017","round":"20","stage_id":"13991081","comp_group":null,"country":"Spain","team_id":"16270","team_name":"Villarreal","status":"same","recent_form":"WLDDW","position":"6","overall_gp":"20","overall_w":"9","overall_d":"7","overall_l":"4","overall_gs":"28","overall_ga":"14","home_gp":"11","home_w":"7","home_d":"2","home_l":"2","home_gs":"20","home_ga":"8","away_gp":"9","away_w":"2","away_d":"5","away_l":"2","away_gs":"8","away_ga":"6","gd":"14","points":"34","description":"Promotion - Europa League (Qualification)"},{"comp_id":"1399","season":"2016/2017","round":"20","stage_id":"13991081","comp_group":null,"country":"Spain","team_id":"15679","team_name":"Ath Bilbao","status":"same","recent_form":"WDDDW","position":"7","overall_gp":"20","overall_w":"9","overall_d":"5","overall_l":"6","overall_gs":"26","overall_ga":"22","home_gp":"11","home_w":"7","home_d":"3","home_l":"1","home_gs":"19","home_ga":"11","away_gp":"9","away_w":"2","away_d":"2","away_l":"5","away_gs":"7","away_ga":"11","gd":"4","points":"32","description":""},{"comp_id":"1399","season":"2016/2017","round":"20","stage_id":"13991081","comp_group":null,"country":"Spain","team_id":"15934","team_name":"Celta Vigo","status":"same","recent_form":"WLWWL","position":"8","overall_gp":"20","overall_w":"9","overall_d":"3","overall_l":"8","overall_gs":"31","overall_ga":"33","home_gp":"10","home_w":"7","home_d":"0","home_l":"3","home_gs":"19","home_ga":"16","away_gp":"10","away_w":"2","away_d":"3","away_l":"5","away_gs":"12","away_ga":"17","gd":"-2","points":"30","description":""},{"comp_id":"1399","season":"2016/2017","round":"20","stage_id":"13991081","comp_group":null,"country":"Spain","team_id":"16009","team_name":"Espanyol","status":"same","recent_form":"WWLDL","position":"9","overall_gp":"20","overall_w":"7","overall_d":"8","overall_l":"5","overall_gs":"28","overall_ga":"27","home_gp":"11","home_w":"4","home_d":"5","home_l":"2","home_gs":"17","home_ga":"13","away_gp":"9","away_w":"3","away_d":"3","away_l":"3","away_gs":"11","away_ga":"14","gd":"1","points":"29","description":""},{"comp_id":"1399","season":"2016/2017","round":"20","stage_id":"13991081","comp_group":null,"country":"Spain","team_id":"16006","team_name":"Eibar","status":"same","recent_form":"WLWLD","position":"10","overall_gp":"20","overall_w":"8","overall_d":"5","overall_l":"7","overall_gs":"28","overall_ga":"29","home_gp":"11","home_w":"6","home_d":"2","home_l":"3","home_gs":"15","home_ga":"13","away_gp":"9","away_w":"2","away_d":"3","away_l":"4","away_gs":"13","away_ga":"16","gd":"-1","points":"29","description":""},{"comp_id":"1399","season":"2016/2017","round":"20","stage_id":"13991081","comp_group":null,"country":"Spain","team_id":"16040","team_name":"Las Palmas","status":"same","recent_form":"WDLWL","position":"11","overall_gp":"20","overall_w":"7","overall_d":"7","overall_l":"6","overall_gs":"31","overall_ga":"31","home_gp":"11","home_w":"6","home_d":"5","home_l":"0","home_gs":"21","home_ga":"10","away_gp":"9","away_w":"1","away_d":"2","away_l":"6","away_gs":"10","away_ga":"21","gd":"0","points":"28","description":""},{"comp_id":"1399","season":"2016/2017","round":"20","stage_id":"13991081","comp_group":null,"country":"Spain","team_id":"15997","team_name":"Alaves","status":"same","recent_form":"DDLDW","position":"12","overall_gp":"20","overall_w":"5","overall_d":"9","overall_l":"6","overall_gs":"17","overall_ga":"20","home_gp":"10","home_w":"2","home_d":"6","home_l":"2","home_gs":"9","home_ga":"10","away_gp":"10","away_w":"3","away_d":"3","away_l":"4","away_gs":"8","away_ga":"10","gd":"-3","points":"24","description":""},{"comp_id":"1399","season":"2016/2017","round":"20","stage_id":"13991081","comp_group":null,"country":"Spain","team_id":"16107","team_name":"Betis","status":"same","recent_form":"DDLWL","position":"13","overall_gp":"20","overall_w":"6","overall_d":"5","overall_l":"9","overall_gs":"21","overall_ga":"31","home_gp":"11","home_w":"4","home_d":"5","home_l":"2","home_gs":"13","home_ga":"13","away_gp":"9","away_w":"2","away_d":"0","away_l":"7","away_gs":"8","away_ga":"18","gd":"-10","points":"23","description":""},{"comp_id":"1399","season":"2016/2017","round":"20","stage_id":"13991081","comp_group":null,"country":"Spain","team_id":"16050","team_name":"Malaga","status":"same","recent_form":"DLLLL","position":"14","overall_gp":"20","overall_w":"5","overall_d":"7","overall_l":"8","overall_gs":"28","overall_ga":"34","home_gp":"9","home_w":"5","home_d":"2","home_l":"2","home_gs":"17","home_ga":"13","away_gp":"11","away_w":"0","away_d":"5","away_l":"6","away_gs":"11","away_ga":"21","gd":"-6","points":"22","description":""},{"comp_id":"1399","season":"2016/2017","round":"20","stage_id":"13991081","comp_group":null,"country":"Spain","team_id":"16261","team_name":"Valencia","status":"same","recent_form":"LWWDL","position":"15","overall_gp":"19","overall_w":"5","overall_d":"4","overall_l":"10","overall_gs":"29","overall_ga":"36","home_gp":"8","home_w":"2","home_d":"2","home_l":"4","home_gs":"13","home_ga":"17","away_gp":"11","away_w":"3","away_d":"2","away_l":"6","away_gs":"16","away_ga":"19","gd":"-7","points":"19","description":""},{"comp_id":"1399","season":"2016/2017","round":"20","stage_id":"13991081","comp_group":null,"country":"Spain","team_id":"15999","team_name":"Dep. La Coruna","status":"same","recent_form":"LDDDW","position":"16","overall_gp":"20","overall_w":"4","overall_d":"7","overall_l":"9","overall_gs":"25","overall_ga":"32","home_gp":"9","home_w":"4","home_d":"2","home_l":"3","home_gs":"15","home_ga":"10","away_gp":"11","away_w":"0","away_d":"5","away_l":"6","away_gs":"10","away_ga":"22","gd":"-7","points":"19","description":""},{"comp_id":"1399","season":"2016/2017","round":"20","stage_id":"13991081","comp_group":null,"country":"Spain","team_id":"15833","team_name":"Leganes","status":"same","recent_form":"LDDLD","position":"17","overall_gp":"20","overall_w":"4","overall_d":"6","overall_l":"10","overall_gs":"15","overall_ga":"33","home_gp":"10","home_w":"1","home_d":"4","home_l":"5","home_gs":"7","home_ga":"15","away_gp":"10","away_w":"3","away_d":"2","away_l":"5","away_gs":"8","away_ga":"18","gd":"-18","points":"18","description":""},{"comp_id":"1399","season":"2016/2017","round":"20","stage_id":"13991081","comp_group":null,"country":"Spain","team_id":"16180","team_name":"Gijon","status":"same","recent_form":"LDLLL","position":"18","overall_gp":"20","overall_w":"3","overall_d":"4","overall_l":"13","overall_gs":"20","overall_ga":"39","home_gp":"9","home_w":"3","home_d":"1","home_l":"5","home_gs":"13","home_ga":"20","away_gp":"11","away_w":"0","away_d":"3","away_l":"8","away_gs":"7","away_ga":"19","gd":"-19","points":"13","description":"Relegation - LaLiga2"},{"comp_id":"1399","season":"2016/2017","round":"20","stage_id":"13991081","comp_group":null,"country":"Spain","team_id":"16079","team_name":"Osasuna","status":"same","recent_form":"DLDDL","position":"19","overall_gp":"20","overall_w":"1","overall_d":"7","overall_l":"12","overall_gs":"21","overall_ga":"43","home_gp":"11","home_w":"0","home_d":"4","home_l":"7","home_gs":"11","home_ga":"23","away_gp":"9","away_w":"1","away_d":"3","away_l":"5","away_gs":"10","away_ga":"20","gd":"-22","points":"10","description":"Relegation - LaLiga2"},{"comp_id":"1399","season":"2016/2017","round":"20","stage_id":"13991081","comp_group":null,"country":"Spain","team_id":"16025","team_name":"Granada CF","status":"same","recent_form":"LLDLL","position":"20","overall_gp":"20","overall_w":"1","overall_d":"7","overall_l":"12","overall_gs":"16","overall_ga":"44","home_gp":"9","home_w":"1","home_d":"4","home_l":"4","home_gs":"7","home_ga":"11","away_gp":"11","away_w":"0","away_d":"3","away_l":"8","away_gs":"9","away_ga":"33","gd":"-28","points":"10","description":"Relegation - LaLiga2"}]